AUTHORS
COPYING
Changelog
MANIFEST.in
README.md
setup.py
bin/lift
doc/lift.rst
doc/lift.yaml.rst
lift/__init__.py
lift/basetest.py
lift/exception.py
lift/loader.py
lift/localtest.py
lift/remotetest.py
lift.egg-info/PKG-INFO
lift.egg-info/SOURCES.txt
lift.egg-info/dependency_links.txt
lift.egg-info/requires.txt
lift.egg-info/top_level.txt