Metadata-Version: 2.1
Name: lift
Version: 2.6.1
Summary: High level test framework
Home-page: https://github.com/Malizor/lift
Author: Nicolas Delvaux
Author-email: contact@nicolas-delvaux.org
License: GPL2+
Download-URL: https://github.com/Malizor/lift/tarball/2.6.1
Keywords: test testing
Platform: UNKNOWN
Classifier: Development Status :: 5 - Production/Stable
Classifier: Intended Audience :: Developers
Classifier: Operating System :: Unix
Classifier: Programming Language :: Python :: 3
Classifier: Environment :: Console
License-File: COPYING
License-File: AUTHORS
